rtstatlib/__init__.py
rtstatlib/__main__.py
rtstatlib/messages.py
rtstatlib/rtstat.py
rtstatlib-1.0.0.dist-info/LICENSE
rtstatlib-1.0.0.dist-info/METADATA
rtstatlib-1.0.0.dist-info/WHEEL
rtstatlib-1.0.0.dist-info/entry_points.txt
rtstatlib-1.0.0.dist-info/top_level.txt
rtstatlib-1.0.0.dist-info/RECORD
